twinlab_client/__init__.py
twinlab_client/client.py
twinlab_client/settings.py
twinlab_client/utils.py
twinlab_client-0.0.0.dist-info/METADATA
twinlab_client-0.0.0.dist-info/WHEEL
twinlab_client-0.0.0.dist-info/RECORD
