Metadata-Version: 2.1
Name: twinlab-client
Version: 0.0.0
Summary: Client interface for twinLab
Home-page: https://github.com/digiLab-ai/twinLab-cloud
Author: Alexander Mead
Author-email: alexander@digilab.co.uk
Requires-Python: >=3.9,<3.10
Classifier: Programming Language :: Python :: 3
Classifier: Programming Language :: Python :: 3.9
Requires-Dist: pandas (>=1.5.3,<2.0.0)
Requires-Dist: pydantic[dotenv] (>=1.10.7,<2.0.0)
Requires-Dist: requests (>=2.28.2,<3.0.0)
Project-URL: Repository, https://github.com/digiLab-ai/twinLab-cloud
